README.txt
setup.cfg
setup.py
Products/__init__.py
Products.ATSchemaEditorNG.egg-info/PKG-INFO
Products.ATSchemaEditorNG.egg-info/SOURCES.txt
Products.ATSchemaEditorNG.egg-info/dependency_links.txt
Products.ATSchemaEditorNG.egg-info/entry_points.txt
Products.ATSchemaEditorNG.egg-info/namespace_packages.txt
Products.ATSchemaEditorNG.egg-info/not-zip-safe
Products.ATSchemaEditorNG.egg-info/requires.txt
Products.ATSchemaEditorNG.egg-info/top_level.txt
Products/ATSchemaEditorNG/ATSETemplateTool.py
Products/ATSchemaEditorNG/ManagedSchema.py
Products/ATSchemaEditorNG/ParentManagedSchema.py
Products/ATSchemaEditorNG/ProductsInstallHelper.py
Products/ATSchemaEditorNG/SchemaEditor.py
Products/ATSchemaEditorNG/SchemaEditorTool.py
Products/ATSchemaEditorNG/SchemplateEditor.py
Products/ATSchemaEditorNG/VERSION.txt
Products/ATSchemaEditorNG/__init__.py
Products/ATSchemaEditorNG/config.py
Products/ATSchemaEditorNG/configure.zcml
Products/ATSchemaEditorNG/interfaces.py
Products/ATSchemaEditorNG/patches.py
Products/ATSchemaEditorNG/tool.jpg
Products/ATSchemaEditorNG/util.py
Products/ATSchemaEditorNG/Extensions/Install.py
Products/ATSchemaEditorNG/examples/__init__.py
Products/ATSchemaEditorNG/examples/content.py
Products/ATSchemaEditorNG/i18n/atschemaeditorng-cs.po
Products/ATSchemaEditorNG/i18n/atschemaeditorng-da.po
Products/ATSchemaEditorNG/i18n/atschemaeditorng-fi.po
Products/ATSchemaEditorNG/i18n/atschemaeditorng-fr.po
Products/ATSchemaEditorNG/i18n/atschemaeditorng.pot
Products/ATSchemaEditorNG/i18n/manual.pot
Products/ATSchemaEditorNG/i18n/plone-fi.po
Products/ATSchemaEditorNG/i18n/usei18ndude.sh
Products/ATSchemaEditorNG/skins/atse_templates/atse_dump_schema.py
Products/ATSchemaEditorNG/skins/atse_templates/atse_editor.pt
Products/ATSchemaEditorNG/skins/atse_templates/atse_field_default.py
Products/ATSchemaEditorNG/skins/atse_templates/atse_macros.pt
Products/ATSchemaEditorNG/skins/atse_templates/atse_main_macro.pt
Products/ATSchemaEditorNG/skins/atse_templates/atse_schemplate_editor.pt
Products/ATSchemaEditorNG/skins/atse_templates/atse_styles.css.dtml
Products/ATSchemaEditorNG/skins/atse_templates/computedfield_postmacro.pt
Products/ATSchemaEditorNG/skins/atse_templates/datagridfield_macros.pt
Products/ATSchemaEditorNG/skins/atse_templates/fileattach_macros.pt
Products/ATSchemaEditorNG/skins/atse_templates/sc_tool.jpg
