Metadata-Version: 1.0
Name: Products.ATSchemaEditorNG
Version: 0.6
Summary: ATSchemaEditorNG is a framework to provide flexible schema editing for AT content-types
Home-page: http://pypi.python.org/pypi/Products.ATSchemaEditorNG
Author: Simon Pamies
Author-email: s.pamies@banality.de
License: LGPL
Keywords: plone archetypes schema
Platform: UNKNOWN
Classifier: Programming Language :: Python
Classifier: Topic :: Software Development :: Libraries :: Python Modules
